bbv/__init__.py
bbv/client.py
bbv/globaldata.py
bbv/main.py
bbv/server.py
bbv/img/icone.png
bbv/img/logo.png
bbv/server/__init__.py
bbv/server/bbv2server.py
bbv/server/html.py
bbv/server/utils.py
bbv/server/views.py
bbv/ui/__init__.py
bbv/ui/gtk.py
bbv/ui/qt.py
bigbashview-3.7.7.data/scripts/bigbashview
bigbashview-3.7.7.dist-info/METADATA
bigbashview-3.7.7.dist-info/WHEEL
bigbashview-3.7.7.dist-info/top_level.txt
bigbashview-3.7.7.dist-info/RECORD
