Metadata-Version: 2.1
Name: bigbashview
Version: 3.7.7
Summary: Graphical Frontends for shellscripts using HTML/JS/CSS
Home-page: https://github.com/biglinux/bigbashview/tree/master/bigbashview/usr/share/bigbashview
Author: eltonff
Author-email: eltonfabricio10@gmail.com
License: GPLv2+
Keywords: big,bigbashview,biglinux,bash,webview,view,web
Classifier: Intended Audience :: Developers
Classifier: License :: OSI Approved :: GNU General Public License v2 or later (GPLv2+)
Classifier: Natural Language :: Portuguese (Brazilian)
Classifier: Programming Language :: Python :: 3
Classifier: Operating System :: OS Independent
Requires-Dist: web.py
Requires-Dist: PyQtWebEngine
Requires-Dist: setproctitle
